juno/__init__.py
juno/__main__.py
juno/juno.py
juno_observer-0.0.1.dist-info/LICENSE
juno_observer-0.0.1.dist-info/METADATA
juno_observer-0.0.1.dist-info/WHEEL
juno_observer-0.0.1.dist-info/entry_points.txt
juno_observer-0.0.1.dist-info/top_level.txt
juno_observer-0.0.1.dist-info/RECORD
