Metadata-Version: 2.1
Name: juno-observer
Version: 0.0.1
Summary: Jupyter file watcher.
Home-page: https://github.com/bicarlsen/juno
Author: Brian Carlsen
Author-email: carlsen.bri@gmail.com
License: UNKNOWN
Project-URL: Documentation, https://github.com/bicarlsen/juno
Project-URL: Source Code, https://github.com/bicarlsen/juno
Project-URL: Bug Tracker, https://github.com/bicarlsen/juno/issues
Platform: UNKNOWN
Classifier: Programming Language :: Python :: 3
Classifier: License :: OSI Approved :: GNU General Public License v3 (GPLv3)
Classifier: Operating System :: OS Independent
